{
  "snapshotTakenAt": "2026-07-02T14:14:39.822Z",
  "isSeed": false,
  "assets": {
    "TSLAon": {
      "symbol": "TSLAon",
      "mint": "KeGv7bsfR4MheC1CkmnAVceoApjrkvBhHYjWb67ondo",
      "holders": 409,
      "priceUsd": 430.2271629043646,
      "marketCapUsd": 127796.94401579273,
      "volume24hUsd": 3274.561006590809,
      "dexLiquidityUsd": 372.6763353715298,
      "lending": [],
      "lendingSupplyUsd": 0,
      "lendingBorrowUsd": 0,
      "defiTvlUsd": 372.6763353715298,
      "slippage": [
        {
          "sizeUsd": 1000,
          "priceImpactPct": null,
          "routable": false
        },
        {
          "sizeUsd": 10000,
          "priceImpactPct": null,
          "routable": false
        },
        {
          "sizeUsd": 100000,
          "priceImpactPct": null,
          "routable": false
        },
        {
          "sizeUsd": 1000000,
          "priceImpactPct": null,
          "routable": false
        }
      ]
    },
    "AMZNon": {
      "symbol": "AMZNon",
      "mint": "14Tqdo8V1FhzKsE3W2pFsZCzYPQxxupXRcqw9jv6ondo",
      "holders": 148,
      "priceUsd": 252.0324229213328,
      "marketCapUsd": 155584.9920371467,
      "volume24hUsd": 84.27415554494762,
      "dexLiquidityUsd": null,
      "lending": [],
      "lendingSupplyUsd": 0,
      "lendingBorrowUsd": 0,
      "defiTvlUsd": 0,
      "slippage": [
        {
          "sizeUsd": 1000,
          "priceImpactPct": null,
          "routable": false
        },
        {
          "sizeUsd": 10000,
          "priceImpactPct": null,
          "routable": false
        },
        {
          "sizeUsd": 100000,
          "priceImpactPct": null,
          "routable": false
        },
        {
          "sizeUsd": 1000000,
          "priceImpactPct": null,
          "routable": false
        }
      ]
    },
    "MSFTon": {
      "symbol": "MSFTon",
      "mint": "FRmH6iRkMr33DLG6zVLR7EM4LojBFAuq6NtFzG6ondo",
      "holders": 220,
      "priceUsd": 393.0376431904942,
      "marketCapUsd": 213044.69756721728,
      "volume24hUsd": 127.95396790081689,
      "dexLiquidityUsd": 241.53084264881272,
      "lending": [],
      "lendingSupplyUsd": 0,
      "lendingBorrowUsd": 0,
      "defiTvlUsd": 241.53084264881272,
      "slippage": [
        {
          "sizeUsd": 1000,
          "priceImpactPct": null,
          "routable": false
        },
        {
          "sizeUsd": 10000,
          "priceImpactPct": null,
          "routable": false
        },
        {
          "sizeUsd": 100000,
          "priceImpactPct": null,
          "routable": false
        },
        {
          "sizeUsd": 1000000,
          "priceImpactPct": null,
          "routable": false
        }
      ]
    },
    "SPYon": {
      "symbol": "SPYon",
      "mint": "k18WJUULWheRkSpSquYGdNNmtuE2Vbw1hpuUi92ondo",
      "holders": 832,
      "priceUsd": 781.1214009757354,
      "marketCapUsd": 95910.51629273083,
      "volume24hUsd": 713.3222096133295,
      "dexLiquidityUsd": 74.17155730880964,
      "lending": [],
      "lendingSupplyUsd": 0,
      "lendingBorrowUsd": 0,
      "defiTvlUsd": 74.17155730880964,
      "slippage": [
        {
          "sizeUsd": 1000,
          "priceImpactPct": 51.275,
          "routable": true
        },
        {
          "sizeUsd": 10000,
          "priceImpactPct": 93.914,
          "routable": true
        },
        {
          "sizeUsd": 100000,
          "priceImpactPct": 99.385,
          "routable": true
        },
        {
          "sizeUsd": 1000000,
          "priceImpactPct": 99.938,
          "routable": true
        }
      ]
    },
    "SPCX": {
      "symbol": "SPCX",
      "mint": "SPCXxcqXj6e5dJDVNovHN8744zkbhM2bYudU45BimGb",
      "holders": 10940,
      "priceUsd": 160.3448820447346,
      "marketCapUsd": 11677793.485460294,
      "volume24hUsd": 35315370.378511354,
      "dexLiquidityUsd": 2365946.444381456,
      "lending": [],
      "lendingSupplyUsd": 0,
      "lendingBorrowUsd": 0,
      "defiTvlUsd": 2365946.444381456,
      "slippage": [
        {
          "sizeUsd": 1000,
          "priceImpactPct": 0.235,
          "routable": true
        },
        {
          "sizeUsd": 10000,
          "priceImpactPct": 0.186,
          "routable": true
        },
        {
          "sizeUsd": 100000,
          "priceImpactPct": 0.18,
          "routable": true
        },
        {
          "sizeUsd": 1000000,
          "priceImpactPct": 2.133,
          "routable": true
        }
      ]
    },
    "SPCXx": {
      "symbol": "SPCXx",
      "mint": "Xs3oZwbHvqis4NYcf4YKWmEia2eC84wSiVrcYcTqpH8",
      "holders": 6350,
      "priceUsd": 160.47277696210014,
      "marketCapUsd": 89864710.19404317,
      "volume24hUsd": 1861796.815792696,
      "dexLiquidityUsd": 182796.97932966865,
      "lending": [],
      "lendingSupplyUsd": 0,
      "lendingBorrowUsd": 0,
      "defiTvlUsd": 182796.97932966865,
      "slippage": [
        {
          "sizeUsd": 1000,
          "priceImpactPct": 0.464,
          "routable": true
        },
        {
          "sizeUsd": 10000,
          "priceImpactPct": 0.942,
          "routable": true
        },
        {
          "sizeUsd": 100000,
          "priceImpactPct": 3.775,
          "routable": true
        },
        {
          "sizeUsd": 1000000,
          "priceImpactPct": 67.452,
          "routable": true
        }
      ]
    },
    "SPACEX": {
      "symbol": "SPACEX",
      "mint": "PreANxuXjsy2pvisWWMNB6YaJNzr7681wJJr2rHsfTh",
      "holders": 11280,
      "priceUsd": 107.38472197752469,
      "marketCapUsd": 4694119.514296121,
      "volume24hUsd": 78944.37789350859,
      "dexLiquidityUsd": 54648.15947808653,
      "lending": [],
      "lendingSupplyUsd": 0,
      "lendingBorrowUsd": 0,
      "defiTvlUsd": 54648.15947808653,
      "slippage": [
        {
          "sizeUsd": 1000,
          "priceImpactPct": 0.344,
          "routable": true
        },
        {
          "sizeUsd": 10000,
          "priceImpactPct": 7.158,
          "routable": true
        },
        {
          "sizeUsd": 100000,
          "priceImpactPct": 19.887,
          "routable": true
        },
        {
          "sizeUsd": 1000000,
          "priceImpactPct": null,
          "routable": false
        }
      ]
    },
    "NVDAx": {
      "symbol": "NVDAx",
      "mint": "Xsc9qvGR1efVDFGLrVsmkzv3qi45LTBjeUKSPmx9qEh",
      "holders": 61109,
      "priceUsd": 199.15486521230818,
      "marketCapUsd": 64043900.243092164,
      "volume24hUsd": 1862421.8139128915,
      "dexLiquidityUsd": 1576359.6358780891,
      "lending": [
        {
          "protocol": "Kamino",
          "market": "xStocks Market",
          "supplyUsd": 2750542,
          "borrowUsd": 20326,
          "utilization": 0.74,
          "supplyApy": 0.03,
          "borrowApy": 3.8,
          "maxLtv": 0.55
        }
      ],
      "lendingSupplyUsd": 2750542,
      "lendingBorrowUsd": 20326,
      "defiTvlUsd": 4326901.635878089,
      "slippage": [
        {
          "sizeUsd": 1000,
          "priceImpactPct": 0.084,
          "routable": true
        },
        {
          "sizeUsd": 10000,
          "priceImpactPct": 0.154,
          "routable": true
        },
        {
          "sizeUsd": 100000,
          "priceImpactPct": 0.756,
          "routable": true
        },
        {
          "sizeUsd": 1000000,
          "priceImpactPct": 6.501,
          "routable": true
        }
      ]
    },
    "NVDAon": {
      "symbol": "NVDAon",
      "mint": "gEGtLTPNQ7jcg25zTetkbmF7teoDLcrfTnQfmn2ondo",
      "holders": 877,
      "priceUsd": 199.33125641988198,
      "marketCapUsd": 2402863.484868109,
      "volume24hUsd": 15338.343988603168,
      "dexLiquidityUsd": 4658.678252007732,
      "lending": [],
      "lendingSupplyUsd": 0,
      "lendingBorrowUsd": 0,
      "defiTvlUsd": 4658.678252007732,
      "slippage": [
        {
          "sizeUsd": 1000,
          "priceImpactPct": null,
          "routable": false
        },
        {
          "sizeUsd": 10000,
          "priceImpactPct": null,
          "routable": false
        },
        {
          "sizeUsd": 100000,
          "priceImpactPct": null,
          "routable": false
        },
        {
          "sizeUsd": 1000000,
          "priceImpactPct": null,
          "routable": false
        }
      ]
    },
    "TSLAx": {
      "symbol": "TSLAx",
      "mint": "XsDoVfqeBukxuZHWhdvWHBhgEHjGNst4MLodqsJHzoB",
      "holders": 26399,
      "priceUsd": 413.3803139736538,
      "marketCapUsd": 94927999.34161161,
      "volume24hUsd": 4002603.7836496173,
      "dexLiquidityUsd": 1957894.8816573548,
      "lending": [
        {
          "protocol": "Kamino",
          "market": "xStocks Market",
          "supplyUsd": 3561871,
          "borrowUsd": 38973,
          "utilization": 1.09,
          "supplyApy": 0.04,
          "borrowApy": 3.81,
          "maxLtv": 0.55
        }
      ],
      "lendingSupplyUsd": 3561871,
      "lendingBorrowUsd": 38973,
      "defiTvlUsd": 5519765.8816573545,
      "slippage": [
        {
          "sizeUsd": 1000,
          "priceImpactPct": 0,
          "routable": true
        },
        {
          "sizeUsd": 10000,
          "priceImpactPct": 0.049,
          "routable": true
        },
        {
          "sizeUsd": 100000,
          "priceImpactPct": 0.678,
          "routable": true
        },
        {
          "sizeUsd": 1000000,
          "priceImpactPct": 6.428,
          "routable": true
        }
      ]
    },
    "AAPLx": {
      "symbol": "AAPLx",
      "mint": "XsbEhLAtcf6HdfpFZ5xEMdqW8nfAvcsP5bdudRLJzJp",
      "holders": 13488,
      "priceUsd": 302.6380080464272,
      "marketCapUsd": 46659249.36676401,
      "volume24hUsd": 57074.48631265049,
      "dexLiquidityUsd": 102772.64029707194,
      "lending": [
        {
          "protocol": "Kamino",
          "market": "xStocks Market",
          "supplyUsd": 366314,
          "borrowUsd": 0,
          "utilization": 0,
          "supplyApy": 0,
          "borrowApy": 3.78,
          "maxLtv": 0.4
        }
      ],
      "lendingSupplyUsd": 366314,
      "lendingBorrowUsd": 0,
      "defiTvlUsd": 469086.64029707195,
      "slippage": [
        {
          "sizeUsd": 1000,
          "priceImpactPct": 0.284,
          "routable": true
        },
        {
          "sizeUsd": 10000,
          "priceImpactPct": 1.334,
          "routable": true
        },
        {
          "sizeUsd": 100000,
          "priceImpactPct": 72.705,
          "routable": true
        },
        {
          "sizeUsd": 1000000,
          "priceImpactPct": 97.634,
          "routable": true
        }
      ]
    },
    "AAPLon": {
      "symbol": "AAPLon",
      "mint": "123mYEnRLM2LLYsJW3K6oyYh8uP1fngj732iG638ondo",
      "holders": 848,
      "priceUsd": 302.27575330354784,
      "marketCapUsd": 86880.53941351538,
      "volume24hUsd": 2788.239940854866,
      "dexLiquidityUsd": 495.41266700136674,
      "lending": [],
      "lendingSupplyUsd": 0,
      "lendingBorrowUsd": 0,
      "defiTvlUsd": 495.41266700136674,
      "slippage": [
        {
          "sizeUsd": 1000,
          "priceImpactPct": null,
          "routable": false
        },
        {
          "sizeUsd": 10000,
          "priceImpactPct": null,
          "routable": false
        },
        {
          "sizeUsd": 100000,
          "priceImpactPct": null,
          "routable": false
        },
        {
          "sizeUsd": 1000000,
          "priceImpactPct": null,
          "routable": false
        }
      ]
    },
    "MSTRx": {
      "symbol": "MSTRx",
      "mint": "XsP7xzNPvEHS1m6qfanPUGjNmdnmsLKEoNAnHjdxxyZ",
      "holders": 8739,
      "priceUsd": 103.89980127631446,
      "marketCapUsd": 35352133.88197186,
      "volume24hUsd": 2914640.0283488706,
      "dexLiquidityUsd": 420530.59088750987,
      "lending": [
        {
          "protocol": "Kamino",
          "market": "xStocks Market",
          "supplyUsd": 1266243,
          "borrowUsd": 0,
          "utilization": 0,
          "supplyApy": 0,
          "borrowApy": 3.78,
          "maxLtv": 0.3
        }
      ],
      "lendingSupplyUsd": 1266243,
      "lendingBorrowUsd": 0,
      "defiTvlUsd": 1686773.5908875098,
      "slippage": [
        {
          "sizeUsd": 1000,
          "priceImpactPct": 0.175,
          "routable": true
        },
        {
          "sizeUsd": 10000,
          "priceImpactPct": 0.386,
          "routable": true
        },
        {
          "sizeUsd": 100000,
          "priceImpactPct": 3.016,
          "routable": true
        },
        {
          "sizeUsd": 1000000,
          "priceImpactPct": 99.691,
          "routable": true
        }
      ]
    },
    "MSTRon": {
      "symbol": "MSTRon",
      "mint": "FSz4ouiqXpHuGPcpacZfTzbMjScoj5FfzHkiyu2ondo",
      "holders": 24,
      "priceUsd": 102.65075339251257,
      "marketCapUsd": 61179.443952723384,
      "volume24hUsd": 42734.20944317256,
      "dexLiquidityUsd": null,
      "lending": [],
      "lendingSupplyUsd": 0,
      "lendingBorrowUsd": 0,
      "defiTvlUsd": 0,
      "slippage": [
        {
          "sizeUsd": 1000,
          "priceImpactPct": null,
          "routable": false
        },
        {
          "sizeUsd": 10000,
          "priceImpactPct": null,
          "routable": false
        },
        {
          "sizeUsd": 100000,
          "priceImpactPct": null,
          "routable": false
        },
        {
          "sizeUsd": 1000000,
          "priceImpactPct": null,
          "routable": false
        }
      ]
    },
    "COINx": {
      "symbol": "COINx",
      "mint": "Xs7ZdzSHLU9ftNJsii5fCeJhoRWSC32SQGzGQtePxNu",
      "holders": 3110,
      "priceUsd": 171.9370739042514,
      "marketCapUsd": 23414376.439831387,
      "volume24hUsd": 736088.9970094862,
      "dexLiquidityUsd": 498354.6300901482,
      "lending": [],
      "lendingSupplyUsd": 0,
      "lendingBorrowUsd": 0,
      "defiTvlUsd": 498354.6300901482,
      "slippage": [
        {
          "sizeUsd": 1000,
          "priceImpactPct": 0.462,
          "routable": true
        },
        {
          "sizeUsd": 10000,
          "priceImpactPct": 0.576,
          "routable": true
        },
        {
          "sizeUsd": 100000,
          "priceImpactPct": 2.22,
          "routable": true
        },
        {
          "sizeUsd": 1000000,
          "priceImpactPct": null,
          "routable": false
        }
      ]
    },
    "COINon": {
      "symbol": "COINon",
      "mint": "5u6KDiNJXxX4rGMfYT4BApZQC5CuDNrG6MHkwp1ondo",
      "holders": 69,
      "priceUsd": 170.401060444661,
      "marketCapUsd": 29801.740927739214,
      "volume24hUsd": 98.35669124098642,
      "dexLiquidityUsd": null,
      "lending": [],
      "lendingSupplyUsd": 0,
      "lendingBorrowUsd": 0,
      "defiTvlUsd": 0,
      "slippage": [
        {
          "sizeUsd": 1000,
          "priceImpactPct": null,
          "routable": false
        },
        {
          "sizeUsd": 10000,
          "priceImpactPct": null,
          "routable": false
        },
        {
          "sizeUsd": 100000,
          "priceImpactPct": null,
          "routable": false
        },
        {
          "sizeUsd": 1000000,
          "priceImpactPct": null,
          "routable": false
        }
      ]
    },
    "AMZNx": {
      "symbol": "AMZNx",
      "mint": "Xs3eBt7uRfJX8QUs4suhyU8p2M6DoUDrJyWBa8LLZsg",
      "holders": 5687,
      "priceUsd": 243.7356726023879,
      "marketCapUsd": 41994725.83658755,
      "volume24hUsd": 161546.59766878752,
      "dexLiquidityUsd": 147568.36136448488,
      "lending": [],
      "lendingSupplyUsd": 0,
      "lendingBorrowUsd": 0,
      "defiTvlUsd": 147568.36136448488,
      "slippage": [
        {
          "sizeUsd": 1000,
          "priceImpactPct": 0.226,
          "routable": true
        },
        {
          "sizeUsd": 10000,
          "priceImpactPct": 0.672,
          "routable": true
        },
        {
          "sizeUsd": 100000,
          "priceImpactPct": 4.69,
          "routable": true
        },
        {
          "sizeUsd": 1000000,
          "priceImpactPct": null,
          "routable": false
        }
      ]
    },
    "MSFTx": {
      "symbol": "MSFTx",
      "mint": "XspzcW1PRtgf6Wj92HCiZdjzKCyFekVD8P5Ueh3dRMX",
      "holders": 3937,
      "priceUsd": 388.01610048450283,
      "marketCapUsd": 40917536.11759906,
      "volume24hUsd": 91028.03542041048,
      "dexLiquidityUsd": 89442.63766781741,
      "lending": [],
      "lendingSupplyUsd": 0,
      "lendingBorrowUsd": 0,
      "defiTvlUsd": 89442.63766781741,
      "slippage": [
        {
          "sizeUsd": 1000,
          "priceImpactPct": 0.074,
          "routable": true
        },
        {
          "sizeUsd": 10000,
          "priceImpactPct": 0.809,
          "routable": true
        },
        {
          "sizeUsd": 100000,
          "priceImpactPct": 6.269,
          "routable": true
        },
        {
          "sizeUsd": 1000000,
          "priceImpactPct": null,
          "routable": false
        }
      ]
    },
    "GOOGLx": {
      "symbol": "GOOGLx",
      "mint": "XsCPL9dNWBMvFtTmwcCA5v3xWPSMEBCszbQdiLLq6aN",
      "holders": 16613,
      "priceUsd": 362.5688399499095,
      "marketCapUsd": 58271050.565290146,
      "volume24hUsd": 484757.51057833945,
      "dexLiquidityUsd": 352202.833992725,
      "lending": [
        {
          "protocol": "Kamino",
          "market": "xStocks Market",
          "supplyUsd": 2265444,
          "borrowUsd": 0,
          "utilization": 0,
          "supplyApy": 0,
          "borrowApy": 3.78,
          "maxLtv": 0.6
        }
      ],
      "lendingSupplyUsd": 2265444,
      "lendingBorrowUsd": 0,
      "defiTvlUsd": 2617646.8339927252,
      "slippage": [
        {
          "sizeUsd": 1000,
          "priceImpactPct": 0.027,
          "routable": true
        },
        {
          "sizeUsd": 10000,
          "priceImpactPct": 0.187,
          "routable": true
        },
        {
          "sizeUsd": 100000,
          "priceImpactPct": 1.549,
          "routable": true
        },
        {
          "sizeUsd": 1000000,
          "priceImpactPct": null,
          "routable": false
        }
      ]
    },
    "GOOGLon": {
      "symbol": "GOOGLon",
      "mint": "bbahNA5vT9WJeYft8tALrH1LXWffjwqVoUbqYa1ondo",
      "holders": 189,
      "priceUsd": 362.2476562879938,
      "marketCapUsd": 2408694.2814180753,
      "volume24hUsd": 20013.827783970384,
      "dexLiquidityUsd": null,
      "lending": [],
      "lendingSupplyUsd": 0,
      "lendingBorrowUsd": 0,
      "defiTvlUsd": 0,
      "slippage": [
        {
          "sizeUsd": 1000,
          "priceImpactPct": null,
          "routable": false
        },
        {
          "sizeUsd": 10000,
          "priceImpactPct": null,
          "routable": false
        },
        {
          "sizeUsd": 100000,
          "priceImpactPct": null,
          "routable": false
        },
        {
          "sizeUsd": 1000000,
          "priceImpactPct": null,
          "routable": false
        }
      ]
    },
    "SPYx": {
      "symbol": "SPYx",
      "mint": "XsoCS1TfEyfFhfvj8EtZ528L3CaKBDBRqRapnBbDF2W",
      "holders": 24700,
      "priceUsd": 751.1500508896312,
      "marketCapUsd": 71944723.90546444,
      "volume24hUsd": 2043762.993241841,
      "dexLiquidityUsd": 3489214.2921883,
      "lending": [
        {
          "protocol": "Kamino",
          "market": "xStocks Market",
          "supplyUsd": 4487517,
          "borrowUsd": 250784,
          "utilization": 5.59,
          "supplyApy": 0.19,
          "borrowApy": 3.92,
          "maxLtv": 0.73
        }
      ],
      "lendingSupplyUsd": 4487517,
      "lendingBorrowUsd": 250784,
      "defiTvlUsd": 7976731.2921883,
      "slippage": [
        {
          "sizeUsd": 1000,
          "priceImpactPct": 0.022,
          "routable": true
        },
        {
          "sizeUsd": 10000,
          "priceImpactPct": 0.092,
          "routable": true
        },
        {
          "sizeUsd": 100000,
          "priceImpactPct": 0.182,
          "routable": true
        },
        {
          "sizeUsd": 1000000,
          "priceImpactPct": 22.137,
          "routable": true
        }
      ]
    }
  }
}
