{
  "snapshotTakenAt": "2026-07-16T03:13:51.996Z",
  "isSeed": false,
  "assets": {
    "TSLAon": {
      "symbol": "TSLAon",
      "mint": "KeGv7bsfR4MheC1CkmnAVceoApjrkvBhHYjWb67ondo",
      "holders": 434,
      "priceUsd": 402.03257946577577,
      "marketCapUsd": 133366.38199138685,
      "volume24hUsd": 31059.902841098836,
      "dexLiquidityUsd": 0.45159019931877026,
      "lending": [],
      "lendingSupplyUsd": 0,
      "lendingBorrowUsd": 0,
      "defiTvlUsd": 0.45159019931877026,
      "slippage": [
        {
          "sizeUsd": 1000,
          "priceImpactPct": null,
          "routable": false
        },
        {
          "sizeUsd": 10000,
          "priceImpactPct": null,
          "routable": false
        },
        {
          "sizeUsd": 100000,
          "priceImpactPct": null,
          "routable": false
        },
        {
          "sizeUsd": 1000000,
          "priceImpactPct": null,
          "routable": false
        }
      ]
    },
    "AMZNon": {
      "symbol": "AMZNon",
      "mint": "14Tqdo8V1FhzKsE3W2pFsZCzYPQxxupXRcqw9jv6ondo",
      "holders": 187,
      "priceUsd": 264.3690518510426,
      "marketCapUsd": 163939.2049164032,
      "volume24hUsd": 704.370142162024,
      "dexLiquidityUsd": 183.06810304402126,
      "lending": [],
      "lendingSupplyUsd": 0,
      "lendingBorrowUsd": 0,
      "defiTvlUsd": 183.06810304402126,
      "slippage": [
        {
          "sizeUsd": 1000,
          "priceImpactPct": null,
          "routable": false
        },
        {
          "sizeUsd": 10000,
          "priceImpactPct": null,
          "routable": false
        },
        {
          "sizeUsd": 100000,
          "priceImpactPct": null,
          "routable": false
        },
        {
          "sizeUsd": 1000000,
          "priceImpactPct": null,
          "routable": false
        }
      ]
    },
    "MSFTon": {
      "symbol": "MSFTon",
      "mint": "FRmH6iRkMr33DLG6zVLR7EM4LojBFAuq6NtFzG6ondo",
      "holders": 233,
      "priceUsd": 395.34407573609104,
      "marketCapUsd": 258541.59224052695,
      "volume24hUsd": 14099.95233689763,
      "dexLiquidityUsd": 241.48008346591527,
      "lending": [],
      "lendingSupplyUsd": 0,
      "lendingBorrowUsd": 0,
      "defiTvlUsd": 241.48008346591527,
      "slippage": [
        {
          "sizeUsd": 1000,
          "priceImpactPct": null,
          "routable": false
        },
        {
          "sizeUsd": 10000,
          "priceImpactPct": null,
          "routable": false
        },
        {
          "sizeUsd": 100000,
          "priceImpactPct": null,
          "routable": false
        },
        {
          "sizeUsd": 1000000,
          "priceImpactPct": null,
          "routable": false
        }
      ]
    },
    "SPYon": {
      "symbol": "SPYon",
      "mint": "k18WJUULWheRkSpSquYGdNNmtuE2Vbw1hpuUi92ondo",
      "holders": 971,
      "priceUsd": 754.1152973923463,
      "marketCapUsd": 153818.16604725012,
      "volume24hUsd": 41818.86064446224,
      "dexLiquidityUsd": 0.011828891373905536,
      "lending": [],
      "lendingSupplyUsd": 0,
      "lendingBorrowUsd": 0,
      "defiTvlUsd": 0.011828891373905536,
      "slippage": [
        {
          "sizeUsd": 1000,
          "priceImpactPct": null,
          "routable": false
        },
        {
          "sizeUsd": 10000,
          "priceImpactPct": null,
          "routable": false
        },
        {
          "sizeUsd": 100000,
          "priceImpactPct": null,
          "routable": false
        },
        {
          "sizeUsd": 1000000,
          "priceImpactPct": null,
          "routable": false
        }
      ]
    },
    "SPCX": {
      "symbol": "SPCX",
      "mint": "SPCXxcqXj6e5dJDVNovHN8744zkbhM2bYudU45BimGb",
      "holders": 10810,
      "priceUsd": 136.04199405713086,
      "marketCapUsd": 8560234.85705219,
      "volume24hUsd": 4697466.527077318,
      "dexLiquidityUsd": 829418.3973680146,
      "lending": [],
      "lendingSupplyUsd": 0,
      "lendingBorrowUsd": 0,
      "defiTvlUsd": 829418.3973680146,
      "slippage": [
        {
          "sizeUsd": 1000,
          "priceImpactPct": 0.072,
          "routable": true
        },
        {
          "sizeUsd": 10000,
          "priceImpactPct": 0.087,
          "routable": true
        },
        {
          "sizeUsd": 100000,
          "priceImpactPct": 0.349,
          "routable": true
        },
        {
          "sizeUsd": 1000000,
          "priceImpactPct": 12.607,
          "routable": true
        }
      ]
    },
    "SPCXx": {
      "symbol": "SPCXx",
      "mint": "Xs3oZwbHvqis4NYcf4YKWmEia2eC84wSiVrcYcTqpH8",
      "holders": 6749,
      "priceUsd": 135.93655382030448,
      "marketCapUsd": 76124425.02225395,
      "volume24hUsd": 623224.356984322,
      "dexLiquidityUsd": 53871.28722912026,
      "lending": [],
      "lendingSupplyUsd": 0,
      "lendingBorrowUsd": 0,
      "defiTvlUsd": 53871.28722912026,
      "slippage": [
        {
          "sizeUsd": 1000,
          "priceImpactPct": 0.203,
          "routable": true
        },
        {
          "sizeUsd": 10000,
          "priceImpactPct": 0.868,
          "routable": true
        },
        {
          "sizeUsd": 100000,
          "priceImpactPct": 4.851,
          "routable": true
        },
        {
          "sizeUsd": 1000000,
          "priceImpactPct": null,
          "routable": false
        }
      ]
    },
    "SPACEX": {
      "symbol": "SPACEX",
      "mint": "PreANxuXjsy2pvisWWMNB6YaJNzr7681wJJr2rHsfTh",
      "holders": 10937,
      "priceUsd": 90.14954774855246,
      "marketCapUsd": 3940696.990587744,
      "volume24hUsd": 54117.395190353156,
      "dexLiquidityUsd": 86383.05184849858,
      "lending": [],
      "lendingSupplyUsd": 0,
      "lendingBorrowUsd": 0,
      "defiTvlUsd": 86383.05184849858,
      "slippage": [
        {
          "sizeUsd": 1000,
          "priceImpactPct": 0.598,
          "routable": true
        },
        {
          "sizeUsd": 10000,
          "priceImpactPct": 3.188,
          "routable": true
        },
        {
          "sizeUsd": 100000,
          "priceImpactPct": 24.288,
          "routable": true
        },
        {
          "sizeUsd": 1000000,
          "priceImpactPct": null,
          "routable": false
        }
      ]
    },
    "NVDAx": {
      "symbol": "NVDAx",
      "mint": "Xsc9qvGR1efVDFGLrVsmkzv3qi45LTBjeUKSPmx9qEh",
      "holders": 61264,
      "priceUsd": 211.7672757984962,
      "marketCapUsd": 68099770.17318831,
      "volume24hUsd": 2443966.050932186,
      "dexLiquidityUsd": 2093329.1192186617,
      "lending": [
        {
          "protocol": "Kamino",
          "market": "xStocks Market",
          "supplyUsd": 3079522,
          "borrowUsd": 18659,
          "utilization": 0.61,
          "supplyApy": 0.02,
          "borrowApy": 3.74,
          "maxLtv": 0.55
        }
      ],
      "lendingSupplyUsd": 3079522,
      "lendingBorrowUsd": 18659,
      "defiTvlUsd": 5172851.119218661,
      "slippage": [
        {
          "sizeUsd": 1000,
          "priceImpactPct": 0.102,
          "routable": true
        },
        {
          "sizeUsd": 10000,
          "priceImpactPct": 0.158,
          "routable": true
        },
        {
          "sizeUsd": 100000,
          "priceImpactPct": 0.687,
          "routable": true
        },
        {
          "sizeUsd": 1000000,
          "priceImpactPct": null,
          "routable": false
        }
      ]
    },
    "NVDAon": {
      "symbol": "NVDAon",
      "mint": "gEGtLTPNQ7jcg25zTetkbmF7teoDLcrfTnQfmn2ondo",
      "holders": 962,
      "priceUsd": 211.63516946965038,
      "marketCapUsd": 2549601.9138719616,
      "volume24hUsd": 15839.926641177139,
      "dexLiquidityUsd": 4456.340316504991,
      "lending": [],
      "lendingSupplyUsd": 0,
      "lendingBorrowUsd": 0,
      "defiTvlUsd": 4456.340316504991,
      "slippage": [
        {
          "sizeUsd": 1000,
          "priceImpactPct": null,
          "routable": false
        },
        {
          "sizeUsd": 10000,
          "priceImpactPct": null,
          "routable": false
        },
        {
          "sizeUsd": 100000,
          "priceImpactPct": null,
          "routable": false
        },
        {
          "sizeUsd": 1000000,
          "priceImpactPct": null,
          "routable": false
        }
      ]
    },
    "TSLAx": {
      "symbol": "TSLAx",
      "mint": "XsDoVfqeBukxuZHWhdvWHBhgEHjGNst4MLodqsJHzoB",
      "holders": 26758,
      "priceUsd": 395.49840605970604,
      "marketCapUsd": 90821608.58942741,
      "volume24hUsd": 2204968.2485392746,
      "dexLiquidityUsd": 1618615.3658621926,
      "lending": [
        {
          "protocol": "Kamino",
          "market": "xStocks Market",
          "supplyUsd": 3264994,
          "borrowUsd": 11720,
          "utilization": 0.36,
          "supplyApy": 0.01,
          "borrowApy": 3.73,
          "maxLtv": 0.55
        }
      ],
      "lendingSupplyUsd": 3264994,
      "lendingBorrowUsd": 11720,
      "defiTvlUsd": 4883609.365862193,
      "slippage": [
        {
          "sizeUsd": 1000,
          "priceImpactPct": 0.012,
          "routable": true
        },
        {
          "sizeUsd": 10000,
          "priceImpactPct": 0.102,
          "routable": true
        },
        {
          "sizeUsd": 100000,
          "priceImpactPct": 0.717,
          "routable": true
        },
        {
          "sizeUsd": 1000000,
          "priceImpactPct": 6.306,
          "routable": true
        }
      ]
    },
    "AAPLx": {
      "symbol": "AAPLx",
      "mint": "XsbEhLAtcf6HdfpFZ5xEMdqW8nfAvcsP5bdudRLJzJp",
      "holders": 13605,
      "priceUsd": 327.2174236684551,
      "marketCapUsd": 50448773.54419498,
      "volume24hUsd": 52549.77376204758,
      "dexLiquidityUsd": 108597.73436631032,
      "lending": [
        {
          "protocol": "Kamino",
          "market": "xStocks Market",
          "supplyUsd": 376183,
          "borrowUsd": 0,
          "utilization": 0,
          "supplyApy": 0,
          "borrowApy": 3.73,
          "maxLtv": 0.4
        }
      ],
      "lendingSupplyUsd": 376183,
      "lendingBorrowUsd": 0,
      "defiTvlUsd": 484780.7343663103,
      "slippage": [
        {
          "sizeUsd": 1000,
          "priceImpactPct": 0.338,
          "routable": true
        },
        {
          "sizeUsd": 10000,
          "priceImpactPct": 14.374,
          "routable": true
        },
        {
          "sizeUsd": 100000,
          "priceImpactPct": 96.184,
          "routable": true
        },
        {
          "sizeUsd": 1000000,
          "priceImpactPct": 99.618,
          "routable": true
        }
      ]
    },
    "AAPLon": {
      "symbol": "AAPLon",
      "mint": "123mYEnRLM2LLYsJW3K6oyYh8uP1fngj732iG638ondo",
      "holders": 988,
      "priceUsd": 328.2227750359871,
      "marketCapUsd": 94088.94826464498,
      "volume24hUsd": 1389.1837764413922,
      "dexLiquidityUsd": 492.69689904581156,
      "lending": [],
      "lendingSupplyUsd": 0,
      "lendingBorrowUsd": 0,
      "defiTvlUsd": 492.69689904581156,
      "slippage": [
        {
          "sizeUsd": 1000,
          "priceImpactPct": null,
          "routable": false
        },
        {
          "sizeUsd": 10000,
          "priceImpactPct": null,
          "routable": false
        },
        {
          "sizeUsd": 100000,
          "priceImpactPct": null,
          "routable": false
        },
        {
          "sizeUsd": 1000000,
          "priceImpactPct": null,
          "routable": false
        }
      ]
    },
    "MSTRx": {
      "symbol": "MSTRx",
      "mint": "XsP7xzNPvEHS1m6qfanPUGjNmdnmsLKEoNAnHjdxxyZ",
      "holders": 8845,
      "priceUsd": 97.8406089758595,
      "marketCapUsd": 39367219.30070104,
      "volume24hUsd": 894198.670129779,
      "dexLiquidityUsd": 427195.5030168501,
      "lending": [
        {
          "protocol": "Kamino",
          "market": "xStocks Market",
          "supplyUsd": 1208867,
          "borrowUsd": 0,
          "utilization": 0,
          "supplyApy": 0,
          "borrowApy": 3.73,
          "maxLtv": 0.3
        }
      ],
      "lendingSupplyUsd": 1208867,
      "lendingBorrowUsd": 0,
      "defiTvlUsd": 1636062.50301685,
      "slippage": [
        {
          "sizeUsd": 1000,
          "priceImpactPct": 0.256,
          "routable": true
        },
        {
          "sizeUsd": 10000,
          "priceImpactPct": 0.536,
          "routable": true
        },
        {
          "sizeUsd": 100000,
          "priceImpactPct": 2.415,
          "routable": true
        },
        {
          "sizeUsd": 1000000,
          "priceImpactPct": null,
          "routable": false
        }
      ]
    },
    "MSTRon": {
      "symbol": "MSTRon",
      "mint": "FSz4ouiqXpHuGPcpacZfTzbMjScoj5FfzHkiyu2ondo",
      "holders": 27,
      "priceUsd": 97.62267154371108,
      "marketCapUsd": 18607.77180298269,
      "volume24hUsd": 516.4815504870451,
      "dexLiquidityUsd": null,
      "lending": [],
      "lendingSupplyUsd": 0,
      "lendingBorrowUsd": 0,
      "defiTvlUsd": 0,
      "slippage": [
        {
          "sizeUsd": 1000,
          "priceImpactPct": null,
          "routable": false
        },
        {
          "sizeUsd": 10000,
          "priceImpactPct": null,
          "routable": false
        },
        {
          "sizeUsd": 100000,
          "priceImpactPct": null,
          "routable": false
        },
        {
          "sizeUsd": 1000000,
          "priceImpactPct": null,
          "routable": false
        }
      ]
    },
    "COINx": {
      "symbol": "COINx",
      "mint": "Xs7ZdzSHLU9ftNJsii5fCeJhoRWSC32SQGzGQtePxNu",
      "holders": 3119,
      "priceUsd": 166.66316872021773,
      "marketCapUsd": 22696175.71839897,
      "volume24hUsd": 429733.9355478203,
      "dexLiquidityUsd": 578397.856809434,
      "lending": [],
      "lendingSupplyUsd": 0,
      "lendingBorrowUsd": 0,
      "defiTvlUsd": 578397.856809434,
      "slippage": [
        {
          "sizeUsd": 1000,
          "priceImpactPct": 0.522,
          "routable": true
        },
        {
          "sizeUsd": 10000,
          "priceImpactPct": 0.859,
          "routable": true
        },
        {
          "sizeUsd": 100000,
          "priceImpactPct": 2.438,
          "routable": true
        },
        {
          "sizeUsd": 1000000,
          "priceImpactPct": null,
          "routable": false
        }
      ]
    },
    "COINon": {
      "symbol": "COINon",
      "mint": "5u6KDiNJXxX4rGMfYT4BApZQC5CuDNrG6MHkwp1ondo",
      "holders": 76,
      "priceUsd": 166.34040237644112,
      "marketCapUsd": 28602.9873409541,
      "volume24hUsd": 499.14956089332077,
      "dexLiquidityUsd": null,
      "lending": [],
      "lendingSupplyUsd": 0,
      "lendingBorrowUsd": 0,
      "defiTvlUsd": 0,
      "slippage": [
        {
          "sizeUsd": 1000,
          "priceImpactPct": null,
          "routable": false
        },
        {
          "sizeUsd": 10000,
          "priceImpactPct": null,
          "routable": false
        },
        {
          "sizeUsd": 100000,
          "priceImpactPct": null,
          "routable": false
        },
        {
          "sizeUsd": 1000000,
          "priceImpactPct": null,
          "routable": false
        }
      ]
    },
    "AMZNx": {
      "symbol": "AMZNx",
      "mint": "Xs3eBt7uRfJX8QUs4suhyU8p2M6DoUDrJyWBa8LLZsg",
      "holders": 5697,
      "priceUsd": 254.72134445823852,
      "marketCapUsd": 43887515.08652817,
      "volume24hUsd": 116478.3593351008,
      "dexLiquidityUsd": 199440.45406206336,
      "lending": [],
      "lendingSupplyUsd": 0,
      "lendingBorrowUsd": 0,
      "defiTvlUsd": 199440.45406206336,
      "slippage": [
        {
          "sizeUsd": 1000,
          "priceImpactPct": 0.123,
          "routable": true
        },
        {
          "sizeUsd": 10000,
          "priceImpactPct": 0.516,
          "routable": true
        },
        {
          "sizeUsd": 100000,
          "priceImpactPct": 4.234,
          "routable": true
        },
        {
          "sizeUsd": 1000000,
          "priceImpactPct": null,
          "routable": false
        }
      ]
    },
    "MSFTx": {
      "symbol": "MSFTx",
      "mint": "XspzcW1PRtgf6Wj92HCiZdjzKCyFekVD8P5Ueh3dRMX",
      "holders": 4017,
      "priceUsd": 398.1172995405587,
      "marketCapUsd": 41982739.792087555,
      "volume24hUsd": 130412.37578704816,
      "dexLiquidityUsd": 105129.6244966343,
      "lending": [],
      "lendingSupplyUsd": 0,
      "lendingBorrowUsd": 0,
      "defiTvlUsd": 105129.6244966343,
      "slippage": [
        {
          "sizeUsd": 1000,
          "priceImpactPct": 0.075,
          "routable": true
        },
        {
          "sizeUsd": 10000,
          "priceImpactPct": 0.738,
          "routable": true
        },
        {
          "sizeUsd": 100000,
          "priceImpactPct": 5.438,
          "routable": true
        },
        {
          "sizeUsd": 1000000,
          "priceImpactPct": null,
          "routable": false
        }
      ]
    },
    "GOOGLx": {
      "symbol": "GOOGLx",
      "mint": "XsCPL9dNWBMvFtTmwcCA5v3xWPSMEBCszbQdiLLq6aN",
      "holders": 17178,
      "priceUsd": 371.83994214008635,
      "marketCapUsd": 59761073.525081135,
      "volume24hUsd": 423413.1822726807,
      "dexLiquidityUsd": 416563.67528345494,
      "lending": [
        {
          "protocol": "Kamino",
          "market": "xStocks Market",
          "supplyUsd": 2808554,
          "borrowUsd": 0,
          "utilization": 0,
          "supplyApy": 0,
          "borrowApy": 3.73,
          "maxLtv": 0.6
        }
      ],
      "lendingSupplyUsd": 2808554,
      "lendingBorrowUsd": 0,
      "defiTvlUsd": 3225117.675283455,
      "slippage": [
        {
          "sizeUsd": 1000,
          "priceImpactPct": 0.103,
          "routable": true
        },
        {
          "sizeUsd": 10000,
          "priceImpactPct": 0.246,
          "routable": true
        },
        {
          "sizeUsd": 100000,
          "priceImpactPct": 1.629,
          "routable": true
        },
        {
          "sizeUsd": 1000000,
          "priceImpactPct": null,
          "routable": false
        }
      ]
    },
    "GOOGLon": {
      "symbol": "GOOGLon",
      "mint": "bbahNA5vT9WJeYft8tALrH1LXWffjwqVoUbqYa1ondo",
      "holders": 210,
      "priceUsd": 381.0987102769216,
      "marketCapUsd": 2510023.5222814535,
      "volume24hUsd": 17994.234154882783,
      "dexLiquidityUsd": 0.0017576573947403046,
      "lending": [],
      "lendingSupplyUsd": 0,
      "lendingBorrowUsd": 0,
      "defiTvlUsd": 0.0017576573947403046,
      "slippage": [
        {
          "sizeUsd": 1000,
          "priceImpactPct": null,
          "routable": false
        },
        {
          "sizeUsd": 10000,
          "priceImpactPct": null,
          "routable": false
        },
        {
          "sizeUsd": 100000,
          "priceImpactPct": null,
          "routable": false
        },
        {
          "sizeUsd": 1000000,
          "priceImpactPct": null,
          "routable": false
        }
      ]
    },
    "SPYx": {
      "symbol": "SPYx",
      "mint": "XsoCS1TfEyfFhfvj8EtZ528L3CaKBDBRqRapnBbDF2W",
      "holders": 25047,
      "priceUsd": 755.5100605227633,
      "marketCapUsd": 72362318.13063249,
      "volume24hUsd": 1963041.4050974238,
      "dexLiquidityUsd": 2506504.257992437,
      "lending": [
        {
          "protocol": "Kamino",
          "market": "xStocks Market",
          "supplyUsd": 4114820,
          "borrowUsd": 229208,
          "utilization": 5.57,
          "supplyApy": 0.19,
          "borrowApy": 3.86,
          "maxLtv": 0.73
        }
      ],
      "lendingSupplyUsd": 4114820,
      "lendingBorrowUsd": 229208,
      "defiTvlUsd": 6621324.257992437,
      "slippage": [
        {
          "sizeUsd": 1000,
          "priceImpactPct": 0.03,
          "routable": true
        },
        {
          "sizeUsd": 10000,
          "priceImpactPct": 0.091,
          "routable": true
        },
        {
          "sizeUsd": 100000,
          "priceImpactPct": 0.562,
          "routable": true
        },
        {
          "sizeUsd": 1000000,
          "priceImpactPct": 43.867,
          "routable": true
        }
      ]
    }
  }
}
